{
    "Category": "in Books (",
    "ListPrice": "",
    "Name": [
        "Vacuum Technology: Calculations in Chemistry"
    ],
    "OfferPrice": "$63.00",
    "Reviews": {
        "AverageStarRating": "0.0 out of 5 stars",
        "ReviewList": [],
        "ReviewUrl": "http://www.amazon.com/Vacuum-Technology-Calculations-David-Hucknall/product-reviews/0854046518/ref=cm_cr_dp_see_all_btm?ie=UTF8&showViewpoints=1&sortBy=helpful",
        "TotalReviewCount": "0"
    },
    "Salesrank": "#2,393,767",
    "Timestamp": "2015-05-24 15:24:21.036810",
    "itemurl": "http://www.amazon.com/Vacuum-Technology-Calculations-David-Hucknall/dp/0854046518"
}
