{
    "Category": "in Video Games (",
    "ListPrice": "",
    "Name": [
        "FIFA Soccer 13 - Xbox 360"
    ],
    "OfferPrice": "",
    "Reviews": {
        "AverageStarRating": "",
        "MaxNumReviews": 15,
        "ReviewList": [
            {
                "Author": {
                    "Helpfulness": "",
                    "Location": "",
                    "Name": "Riley Refuerzo",
                    "ProfileUrl": "http://www.amazon.com/gp/pdp/profile/A388BXVRZ7VDV0/ref=cm_cr_pr_pdp?ie=UTF8",
                    "Ranking": ""
                },
                "Date": "on May 18, 2015",
                "Helpfulness": "",
                "StarRating": "5",
                "Text": "Great game. Fast delivery. Good condition. Very good!"
            },
            {
                "Author": {
                    "Helpfulness": "100%",
                    "Location": "",
                    "Name": "slumv88",
                    "ProfileUrl": "http://www.amazon.com/gp/pdp/profile/A1NR87GEX5CF3B/ref=cm_cr_pr_pdp?ie=UTF8",
                    "Ranking": "Reviewer ranking: #794,917"
                },
                "Date": "on May 1, 2015",
                "Helpfulness": "",
                "StarRating": "5",
                "Text": "I am a huge fan of the FIFA titles, and this does not disappoint.  Both the single player and multiplayer modes were very enjoyable.  I spent most of my time playing online.  The graphics are stunning and players look fairly realistic.  I would highly recommend this product."
            },
            {
                "Author": {
                    "Helpfulness": "0%",
                    "Location": "",
                    "Name": "Eduardo quinonez",
                    "ProfileUrl": "http://www.amazon.com/gp/pdp/profile/A337FBV72VBBSB/ref=cm_cr_pr_pdp?ie=UTF8",
                    "Ranking": "Reviewer ranking: #15,505,160"
                },
                "Date": "on April 24, 2015",
                "Helpfulness": "",
                "StarRating": "5",
                "Text": "Excellent Product"
            },
            {
                "Author": {
                    "Helpfulness": "77%",
                    "Location": "",
                    "Name": "Buyer of Stuff",
                    "ProfileUrl": "http://www.amazon.com/gp/pdp/profile/A2CDK1VTD80WM6/ref=cm_cr_pr_pdp?ie=UTF8",
                    "Ranking": "Reviewer ranking: #131,016"
                },
                "Date": "on April 18, 2015",
                "Helpfulness": "",
                "StarRating": "5",
                "Text": "Kid loves it!"
            },
            {
                "Author": {
                    "Helpfulness": "63%",
                    "Location": "",
                    "Name": "Julian Roo",
                    "ProfileUrl": "http://www.amazon.com/gp/pdp/profile/A2EY7WUQJS64X5/ref=cm_cr_pr_pdp?ie=UTF8",
                    "Ranking": "Reviewer ranking: #873,606"
                },
                "Date": "on April 13, 2015",
                "Helpfulness": "",
                "StarRating": "4",
                "Text": null
            },
            {
                "Author": {
                    "Helpfulness": "33%",
                    "Location": "Venezuela",
                    "Name": "Idelfonso Silva",
                    "ProfileUrl": "http://www.amazon.com/gp/pdp/profile/A2TVE9UESQRETI/ref=cm_cr_pr_pdp?ie=UTF8",
                    "Ranking": "Reviewer ranking: #24,698,514"
                },
                "Date": "on April 9, 2015",
                "Helpfulness": "",
                "StarRating": "5",
                "Text": "Excelente Product! I recommend it 100%"
            },
            {
                "Author": {
                    "Helpfulness": "0%",
                    "Location": "",
                    "Name": "DAVID BOLIVAR",
                    "ProfileUrl": "http://www.amazon.com/gp/pdp/profile/A28EE5ZHBS3D9D/ref=cm_cr_pr_pdp?ie=UTF8",
                    "Ranking": "Reviewer ranking: #18,464,606"
                },
                "Date": "on March 30, 2015",
                "Helpfulness": "",
                "StarRating": "5",
                "Text": "EXCELLENT !!!"
            },
            {
                "Author": {
                    "Helpfulness": "67%",
                    "Location": "california, usa",
                    "Name": "mike r",
                    "ProfileUrl": "http://www.amazon.com/gp/pdp/profile/A1OY1E8AIH9C5H/ref=cm_cr_pr_pdp?ie=UTF8",
                    "Ranking": "Reviewer ranking: #510,656"
                },
                "Date": "on March 20, 2015",
                "Helpfulness": "",
                "StarRating": "5",
                "Text": "AAA+++"
            },
            {
                "Author": {
                    "Helpfulness": "44%",
                    "Location": "Ramona CA",
                    "Name": "Alejandro V. Moreno",
                    "ProfileUrl": "http://www.amazon.com/gp/pdp/profile/AQXMW6VHFUMYS/ref=cm_cr_pr_pdp?ie=UTF8",
                    "Ranking": "Reviewer ranking: #31,156,163"
                },
                "Date": "on March 10, 2015",
                "Helpfulness": "",
                "StarRating": "5",
                "Text": "Good"
            },
            {
                "Author": {
                    "Helpfulness": "",
                    "Location": "",
                    "Name": "Joe B",
                    "ProfileUrl": "http://www.amazon.com/gp/pdp/profile/AEE9DVRZ29E4H/ref=cm_cr_pr_pdp?ie=UTF8",
                    "Ranking": "Reviewer ranking: #2,346,466"
                },
                "Date": "on March 1, 2015",
                "Helpfulness": "",
                "StarRating": "5",
                "Text": "Excellent Product and fast shipping 5+++++!"
            },
            {
                "Author": {
                    "Helpfulness": "40%",
                    "Location": "",
                    "Name": "mohammed hashim",
                    "ProfileUrl": "http://www.amazon.com/gp/pdp/profile/ATWW83XHV196L/ref=cm_cr_pr_pdp?ie=UTF8",
                    "Ranking": "Reviewer ranking: #2,700,047"
                },
                "Date": "on March 1, 2015",
                "Helpfulness": "",
                "StarRating": "5",
                "Text": "Deliver in time and love it"
            },
            {
                "Author": {
                    "Helpfulness": "13%",
                    "Location": "",
                    "Name": "cristian",
                    "ProfileUrl": "http://www.amazon.com/gp/pdp/profile/A1NH1EFVPRZWA/ref=cm_cr_pr_pdp?ie=UTF8",
                    "Ranking": "Reviewer ranking: #31,277,605"
                },
                "Date": "on February 28, 2015",
                "Helpfulness": "",
                "StarRating": "5",
                "Text": "ok"
            },
            {
                "Author": {
                    "Helpfulness": "",
                    "Location": "",
                    "Name": "ROBERTO AGRAZ",
                    "ProfileUrl": "http://www.amazon.com/gp/pdp/profile/A1AVYMF8YJIDBA/ref=cm_cr_pr_pdp?ie=UTF8",
                    "Ranking": "Reviewer ranking: #2,172,359"
                },
                "Date": "on February 28, 2015",
                "Helpfulness": "",
                "StarRating": "5",
                "Text": "Excelente"
            },
            {
                "Author": {
                    "Helpfulness": "80%",
                    "Location": "",
                    "Name": "B. Olund",
                    "ProfileUrl": "http://www.amazon.com/gp/pdp/profile/A2D3K461HOHJE1/ref=cm_cr_pr_pdp?ie=UTF8",
                    "Ranking": "Reviewer ranking: #1,072,808"
                },
                "Date": "on February 23, 2015",
                "Helpfulness": "",
                "StarRating": "5",
                "Text": "Great game, everyone should have this in their collection!"
            },
            {
                "Author": {
                    "Helpfulness": "0%",
                    "Location": "",
                    "Name": "Julio Vetancourt",
                    "ProfileUrl": "http://www.amazon.com/gp/pdp/profile/AS0BQZUPIUX24/ref=cm_cr_pr_pdp?ie=UTF8",
                    "Ranking": "Reviewer ranking: #31,062,001"
                },
                "Date": "on February 15, 2015",
                "Helpfulness": "",
                "StarRating": "4",
                "Text": "very nice"
            },
            {
                "Author": {
                    "Helpfulness": "33%",
                    "Location": "",
                    "Name": "lorena",
                    "ProfileUrl": "http://www.amazon.com/gp/pdp/profile/A3W3H2GX80XMIV/ref=cm_cr_pr_pdp?ie=UTF8",
                    "Ranking": "Reviewer ranking: #31,135,537"
                },
                "Date": "on February 12, 2015",
                "Helpfulness": "",
                "StarRating": "4",
                "Text": "Happy with it :)"
            },
            {
                "Author": {
                    "Helpfulness": "50%",
                    "Location": "",
                    "Name": "Humberto de Mattos Grimaldi Jr",
                    "ProfileUrl": "http://www.amazon.com/gp/pdp/profile/A343CEQ523FNYK/ref=cm_cr_pr_pdp?ie=UTF8",
                    "Ranking": "Reviewer ranking: #28,811,000"
                },
                "Date": "on February 10, 2015",
                "Helpfulness": "",
                "StarRating": "5",
                "Text": "Fantastic product !!"
            },
            {
                "Author": {
                    "Helpfulness": "0%",
                    "Location": "Brownsville, Wisconsin United States",
                    "Name": "Terri",
                    "ProfileUrl": "http://www.amazon.com/gp/pdp/profile/A1XBOOVAS9Q591/ref=cm_cr_pr_pdp?ie=UTF8",
                    "Ranking": "Reviewer ranking: #31,206,755"
                },
                "Date": "on February 5, 2015",
                "Helpfulness": "",
                "StarRating": "4",
                "Text": "given as gift"
            },
            {
                "Author": {
                    "Helpfulness": "80%",
                    "Location": "",
                    "Name": "Danny",
                    "ProfileUrl": "http://www.amazon.com/gp/pdp/profile/AHENS0FHCKEJ8/ref=cm_cr_pr_pdp?ie=UTF8",
                    "Ranking": "Reviewer ranking: #1,693,832"
                },
                "Date": "on January 30, 2015",
                "Helpfulness": "",
                "StarRating": "5",
                "Text": "excellent condition no scratches and has been working and it's 2015 now"
            },
            {
                "Author": {
                    "Helpfulness": "57%",
                    "Location": "",
                    "Name": "boxer909",
                    "ProfileUrl": "http://www.amazon.com/gp/pdp/profile/A3UZSOWUQ5RAP5/ref=cm_cr_pr_pdp?ie=UTF8",
                    "Ranking": "Reviewer ranking: #21,685,408"
                },
                "Date": "on January 17, 2015",
                "Helpfulness": "",
                "StarRating": "5",
                "Text": "To me this is the best FIFA ever made."
            }
        ],
        "ReviewUrl": "http://www.amazon.com/FIFA-Soccer-13-Xbox-360/product-reviews/B008277M0Y/ref=cm_cr_dp_see_all_btm?ie=UTF8&showViewpoints=1&sortBy=bySubmissionDateDescending"
    },
    "Salesrank": "#1,996",
    "Timestamp": "2015-05-21 23:12:09.790721",
    "itemurl": "http://www.amazon.com/FIFA-Soccer-13-Xbox-360/dp/B008277M0Y/ref=sr_1_5?s=videogames&ie=UTF8&qid=1432264199&sr=1-5&keywords=FIFA"
}
