{"Category": "", "Name": "", "Timestamp": "2015-05-23 13:22:06.725003", "itemurl": "http://www.amazon.com/Groups-Pedestrians-Dover-Books-Physics/dp/0486421856/ref=sr_1_172?s=books&ie=UTF8&qid=1432393601&sr=1-172&keywords=physics+books+paperback", "Reviews": {"TotalReviewCount": "", "ReviewList": [], "ReviewUrl": "http://www.amazon.com/Groups-Pedestrians-Dover-Books-Physics/product-reviews/0486421856/ref=sr_1_172?s=books&ie=UTF8&qid=1432393601&sr=1-172&keywords=physics+books+paperback/ref=cm_cr_dp_see_all_btm?ie=UTF8&showViewpoints=1&sortBy=helpful", "AverageStarRating": ""}, "OfferPrice": "", "Salesrank": "", "ListPrice": ""}