{"Category": "in Books (", "Name": ["Quantum Physics: A Beginner's Guide (Beginner's Guides)"], "Timestamp": "2015-05-23 13:19:03.718972", "itemurl": "http://www.amazon.com/Quantum-Physics-Beginners-Guide-Guides/dp/1851683690/ref=sr_1_10?s=books&ie=UTF8&qid=1432393584&sr=1-10&keywords=physics+books+paperback", "Reviews": {"TotalReviewCount": "", "ReviewList": [], "ReviewUrl": "http://www.amazon.com/Quantum-Physics-Beginners-Guide-Guides/product-reviews/1851683690/ref=sr_1_10?s=books&ie=UTF8&qid=1432393584&sr=1-10&keywords=physics+books+paperback/ref=cm_cr_dp_see_all_btm?ie=UTF8&showViewpoints=1&sortBy=helpful", "AverageStarRating": ""}, "OfferPrice": "$12.81", "Salesrank": "#26,238", "ListPrice": "$14.95"}