{"Category": "", "Name": "", "Timestamp": "2015-05-23 13:22:43.806914", "itemurl": "http://www.amazon.com/Lightning-Discharge-Dover-Books-Physics/dp/0486414639/ref=sr_1_297?s=books&ie=UTF8&qid=1432393614&sr=1-297&keywords=physics+books+paperback", "Reviews": {"TotalReviewCount": "", "ReviewList": [], "ReviewUrl": "http://www.amazon.com/Lightning-Discharge-Dover-Books-Physics/product-reviews/0486414639/ref=sr_1_297?s=books&ie=UTF8&qid=1432393614&sr=1-297&keywords=physics+books+paperback/ref=cm_cr_dp_see_all_btm?ie=UTF8&showViewpoints=1&sortBy=helpful", "AverageStarRating": ""}, "OfferPrice": "", "Salesrank": "", "ListPrice": ""}