{
    "Category": "in Books (",
    "ListPrice": "$39.80",
    "Name": [
        "Student's Workbook for College Physics: A Strategic Approach Volume 2 (Chs. 17-30)"
    ],
    "OfferPrice": "$37.81",
    "Reviews": {
        "AverageStarRating": "0.0 out of 5 stars",
        "ReviewList": [],
        "ReviewUrl": "http://www.amazon.com/Students-Workbook-College-Physics-Strategic/product-reviews/0321908872/ref=cm_cr_dp_see_all_btm?ie=UTF8&showViewpoints=1&sortBy=helpful",
        "TotalReviewCount": "0"
    },
    "Salesrank": "#413,131",
    "Timestamp": "2015-05-24 13:22:12.018611",
    "itemurl": "http://www.amazon.com/Students-Workbook-College-Physics-Strategic/dp/0321908872"
}
