{
    "Category": "in Books (",
    "ListPrice": "$19.95",
    "Name": [
        "Tensor Analysis for Physicists, Second Edition (Dover Books on Physics)"
    ],
    "OfferPrice": "$16.86",
    "Reviews": {
        "AverageStarRating": "3.5 out of 5 stars",
        "ReviewList": [
            {
                "Author": {
                    "ProfileUrl": "http://www.amazon.com/gp/pdp/profile/A86WXTHM4IZJD"
                },
                "Date": "on July 31, 2002",
                "Helpfulness": 0.9642857142857143,
                "StarRating": "4",
                "Text": null
            },
            {
                "Author": {
                    "ProfileUrl": "http://www.amazon.com/gp/pdp/profile/A359ALKXLDSYS7"
                },
                "Date": "on November 20, 2013",
                "Helpfulness": 1.0,
                "StarRating": "3",
                "Text": "The book, though thorough, did not meet my expectations for the application-based approach that I expected from a book aimed at Physicists instead of pure Mathematicians.  Also, the type style/font employed made it difficult to read in many places."
            },
            {
                "Author": {
                    "ProfileUrl": "http://www.amazon.com/gp/pdp/profile/A1J1RAZQ48WAQM"
                },
                "Date": "on January 5, 2015",
                "Helpfulness": "",
                "StarRating": "2",
                "Text": "This is tensor analysis for physicists, written from the point of view of a mathematician.  Not of much use for a physicist."
            },
            {
                "Author": {
                    "ProfileUrl": "http://www.amazon.com/gp/pdp/profile/A2ANAI6AIORZU8"
                },
                "Date": "on August 26, 2000",
                "Helpfulness": 0.3,
                "StarRating": "5",
                "Text": "I would suggest this book for relativity lovers, who loves to undrestand  General relativity deeply. This book is easy to learn and it takes very  little time to read but the benefits are very large."
            }
        ],
        "ReviewUrl": "http://www.amazon.com/Tensor-Analysis-Physicists-Second-Physics/product-reviews/0486655822/ref=cm_cr_dp_see_all_btm?ie=UTF8&showViewpoints=1&sortBy=helpful",
        "TotalReviewCount": "4"
    },
    "Salesrank": "#1,449,514",
    "Timestamp": "2015-05-24 13:17:58.324545",
    "itemurl": "http://www.amazon.com/Tensor-Analysis-Physicists-Second-Physics/dp/0486655822"
}
