{
    "Category": "in Books (",
    "ListPrice": "$120.00",
    "Name": [
        "Neutrinos in High Energy and Astroparticle Physics"
    ],
    "OfferPrice": "$105.59",
    "Reviews": {
        "AverageStarRating": "0.0 out of 5 stars",
        "ReviewList": [],
        "ReviewUrl": "http://www.amazon.com/Neutrinos-High-Energy-Astroparticle-Physics/product-reviews/3527411976/ref=cm_cr_dp_see_all_btm?ie=UTF8&showViewpoints=1&sortBy=helpful",
        "TotalReviewCount": "0"
    },
    "Salesrank": "#816,857",
    "Timestamp": "2015-05-24 13:28:28.478748",
    "itemurl": "http://www.amazon.com/Neutrinos-High-Energy-Astroparticle-Physics/dp/3527411976"
}
