{
    "Category": "in Books (",
    "ListPrice": "",
    "Name": [
        "Kernel Functions and Elliptic Differential Equations in Mathematical Physics (Dover Books on Mathematics)"
    ],
    "OfferPrice": "",
    "Reviews": {
        "AverageStarRating": "0.0 out of 5 stars",
        "ReviewList": [],
        "ReviewUrl": "http://www.amazon.com/Functions-Differential-Equations-Mathematical-Mathematics/product-reviews/B007K514RQ/ref=sr_1_104?s=books&ie=UTF8&qid=1432362060&sr=1-104&keywords=mathematics+books+paperback/ref=cm_cr_dp_see_all_btm?ie=UTF8&showViewpoints=1&sortBy=helpful",
        "TotalReviewCount": "0"
    },
    "Salesrank": "#1,770,823",
    "Timestamp": "2015-05-23 02:28:11.081264",
    "itemurl": "http://www.amazon.com/Functions-Differential-Equations-Mathematical-Mathematics/dp/B007K514RQ/ref=sr_1_104?s=books&ie=UTF8&qid=1432362060&sr=1-104&keywords=mathematics+books+paperback"
}
